yeectl/__init__.py
yeectl/__main__.py
yeectl-0.0.3.dist-info/LICENSE
yeectl-0.0.3.dist-info/METADATA
yeectl-0.0.3.dist-info/WHEEL
yeectl-0.0.3.dist-info/top_level.txt
yeectl-0.0.3.dist-info/RECORD
