Metadata-Version: 2.1
Name: yeectl
Version: 0.0.3
Summary: Python TUI for controlling Yeelights
Author-email: Bean Robinson <beanrobinson@duck.com>
License: The MIT License (MIT)
Project-URL: GitHub, https://github.com/Bean499/yeectl
Classifier: Programming Language :: Python :: 3
Classifier: License :: OSI Approved :: MIT License
Classifier: Operating System :: OS Independent
Requires-Python: >=3.7
License-File: LICENSE
